<?xml version="1.0" encoding="utf-8" ?>
<dwsync>
<file name="bg.png" server="qxu1152040046.my3w.com//htdocs/" local="130866655200000000" remote="130866655200000000" Dst="0" />
<file name="center_focus.jpg" server="qxu1152040046.my3w.com//htdocs/" local="130866655200000000" remote="130866655200000000" Dst="0" />
<file name="file-icons.gif" server="qxu1152040046.my3w.com//htdocs/" local="130866655200000000" remote="130866655200000000" Dst="0" />
<file name="icons.gif" server="qxu1152040046.my3w.com//htdocs/" local="130866655200000000" remote="130866655200000000" Dst="0" />
<file name="icons.png" server="qxu1152040046.my3w.com//htdocs/" local="130866655200000000" remote="130866655200000000" Dst="0" />
<file name="file-icons.png" server="qxu1152040046.my3w.com//htdocs/" local="130866655200000000" remote="130866655200000000" Dst="0" />
<file name="image.png" server="qxu1152040046.my3w.com//htdocs/" local="130866655200000000" remote="130866655200000000" Dst="0" />
<file name="left_focus.jpg" server="qxu1152040046.my3w.com//htdocs/" local="130866655200000000" remote="130866655200000000" Dst="0" />
<file name="none_focus.jpg" server="qxu1152040046.my3w.com//htdocs/" local="130866655200000000" remote="130866655200000000" Dst="0" />
<file name="progress.png" server="qxu1152040046.my3w.com//htdocs/" local="130866655200000000" remote="130866655200000000" Dst="0" />
<file name="right_focus.jpg" server="qxu1152040046.my3w.com//htdocs/" local="130866655200000000" remote="130866655200000000" Dst="0" />
<file name="success.gif" server="qxu1152040046.my3w.com//htdocs/" local="130866655200000000" remote="130866655200000000" Dst="0" />
<file name="success.png" server="qxu1152040046.my3w.com//htdocs/" local="130866655200000000" remote="130866655200000000" Dst="0" />
</dwsync>